CHANGELOG.txt
LICENCE.txt
MANIFEST.in
README.md
setup.py
PyMails/__init__.py
PyMails.egg-info/PKG-INFO
PyMails.egg-info/SOURCES.txt
PyMails.egg-info/dependency_links.txt
PyMails.egg-info/top_level.txt