Metadata-Version: 2.1
Name: PyMails
Version: 0.0.5
Summary: Simple tools for sending mail
Home-page: https://github.com/MrJacob12/PyMails
Author: MrJacob
Author-email: jacob@fern.fun
License: MIT
Keywords: email
Platform: UNKNOWN
Classifier: Development Status :: 5 - Production/Stable
Classifier: Intended Audience :: Education
Classifier: Operating System :: Microsoft :: Windows :: Windows 10
Classifier: License :: OSI Approved :: MIT License
Classifier: Programming Language :: Python :: 3
